{"matchId":"448b478b-ffc8-4020-b1e4-b1e4034ad6b2.nakama-0","mapId":"AmbroseValley","date":"2026-02-14","startTs":1771054381,"durationSec":229,"humanCount":1,"botCount":0,"eventCounts":{"Position":35,"Loot":17,"BotKilled":1},"users":[{"id":"1c80d8b9-cca0-4183-9fab-719eeda4a193","isBot":false,"path":[[0,268.38,-50.59],[25,239.41,-48.54],[30,239.59,-29.8],[40,216.43,-12.92],[45,197.33,-17.78],[50,178.96,-42.71],[55,166.95,-64.38],[60,165.26,-65.92],[65,162.39,-63.33],[90,158.76,-66.06],[95,142.78,-64.46],[100,143.3,-72.34],[105,149.71,-70.7],[110,158.32,-70.86],[115,151.74,-77.68],[120,149.92,-75.57],[125,155.7,-75.94],[130,161.87,-69.72],[135,157.47,-80.24],[140,162.78,-79.84],[145,153.03,-93.13],[155,149.84,-90.98],[161,137.48,-86.89],[166,123.08,-97.28],[171,103.24,-87.94],[176,96.26,-85.93],[181,90.93,-86.35],[186,87.32,-80.08],[191,87.0,-77.03],[196,93.49,-79.3],[201,97.88,-68.96],[206,98.39,-59.3],[211,89.92,-65.68],[216,92.06,-66.14],[221,86.78,-77.72]]}],"events":[{"t":61,"x":165.26,"z":-65.92,"type":"Loot","user":"1c80d8b9-cca0-4183-9fab-719eeda4a193","isBot":false},{"t":82,"x":162.03,"z":-62.75,"type":"Loot","user":"1c80d8b9-cca0-4183-9fab-719eeda4a193","isBot":false},{"t":84,"x":160.99,"z":-61.65,"type":"Loot","user":"1c80d8b9-cca0-4183-9fab-719eeda4a193","isBot":false},{"t":112,"x":152.81,"z":-74.18,"type":"Loot","user":"1c80d8b9-cca0-4183-9fab-719eeda4a193","isBot":false},{"t":114,"x":151.74,"z":-77.68,"type":"Loot","user":"1c80d8b9-cca0-4183-9fab-719eeda4a193","isBot":false},{"t":120,"x":149.92,"z":-75.57,"type":"Loot","user":"1c80d8b9-cca0-4183-9fab-719eeda4a193","isBot":false},{"t":121,"x":149.92,"z":-75.57,"type":"Loot","user":"1c80d8b9-cca0-4183-9fab-719eeda4a193","isBot":false},{"t":131,"x":161.87,"z":-69.72,"type":"Loot","user":"1c80d8b9-cca0-4183-9fab-719eeda4a193","isBot":false},{"t":148,"x":148.81,"z":-94.82,"type":"Loot","user":"1c80d8b9-cca0-4183-9fab-719eeda4a193","isBot":false},{"t":153,"x":151.36,"z":-90.15,"type":"Loot","user":"1c80d8b9-cca0-4183-9fab-719eeda4a193","isBot":false},{"t":157,"x":143.32,"z":-92.95,"type":"Loot","user":"1c80d8b9-cca0-4183-9fab-719eeda4a193","isBot":false},{"t":174,"x":96.54,"z":-85.45,"type":"Loot","user":"1c80d8b9-cca0-4183-9fab-719eeda4a193","isBot":false},{"t":174,"x":96.54,"z":-85.45,"type":"Loot","user":"1c80d8b9-cca0-4183-9fab-719eeda4a193","isBot":false},{"t":191,"x":87.0,"z":-77.03,"type":"Loot","user":"1c80d8b9-cca0-4183-9fab-719eeda4a193","isBot":false},{"t":193,"x":91.7,"z":-78.27,"type":"Loot","user":"1c80d8b9-cca0-4183-9fab-719eeda4a193","isBot":false},{"t":198,"x":95.85,"z":-76.31,"type":"Loot","user":"1c80d8b9-cca0-4183-9fab-719eeda4a193","isBot":false},{"t":202,"x":101.41,"z":-67.88,"type":"Loot","user":"1c80d8b9-cca0-4183-9fab-719eeda4a193","isBot":false},{"t":229,"x":87.17,"z":-77.76,"type":"BotKilled","user":"1c80d8b9-cca0-4183-9fab-719eeda4a193","isBot":false}]}