{"matchId":"525deef0-21fb-4f5d-a590-732dda137bdb.nakama-0","mapId":"AmbroseValley","date":"2026-02-10","startTs":1770707389,"durationSec":282,"humanCount":1,"botCount":0,"eventCounts":{"Position":47,"Loot":16,"BotKill":3},"users":[{"id":"a58b4a5f-0add-43fe-b986-1cea83120c5a","isBot":false,"path":[[0,-300.86,-355.44],[15,-295.48,-351.95],[20,-277.84,-344.44],[25,-255.52,-337.95],[30,-236.09,-326.09],[35,-229.89,-330.48],[40,-223.62,-350.31],[45,-223.7,-341.56],[50,-223.67,-333.08],[55,-228.42,-331.93],[60,-221.73,-323.57],[70,-210.79,-308.0],[76,-187.9,-306.06],[81,-180.8,-304.85],[86,-175.98,-312.94],[91,-149.91,-298.7],[96,-125.08,-284.38],[101,-105.9,-273.77],[106,-102.9,-273.49],[111,-88.08,-273.47],[116,-81.34,-279.81],[121,-49.82,-275.27],[126,-22.21,-281.31],[131,-17.99,-295.44],[136,-6.87,-287.96],[141,-0.83,-277.25],[146,-9.13,-277.56],[151,-5.78,-278.18],[156,-0.61,-279.73],[161,-8.95,-284.99],[166,-17.39,-281.1],[171,-14.43,-278.0],[176,-13.62,-281.43],[206,-17.81,-280.65],[211,-15.69,-269.01],[216,-13.21,-279.62],[221,-14.18,-280.88],[231,-15.29,-279.63],[236,-7.51,-289.96],[241,-8.14,-299.28],[247,5.76,-285.49],[252,24.38,-289.44],[257,48.96,-298.35],[262,52.77,-295.3],[272,49.47,-297.92],[277,71.27,-305.24],[282,68.76,-308.94]]}],"events":[{"t":34,"x":-226.99,"z":-328.78,"type":"Loot","user":"a58b4a5f-0add-43fe-b986-1cea83120c5a","isBot":false},{"t":43,"x":-216.82,"z":-343.21,"type":"Loot","user":"a58b4a5f-0add-43fe-b986-1cea83120c5a","isBot":false},{"t":57,"x":-228.42,"z":-331.93,"type":"Loot","user":"a58b4a5f-0add-43fe-b986-1cea83120c5a","isBot":false},{"t":57,"x":-228.42,"z":-331.93,"type":"Loot","user":"a58b4a5f-0add-43fe-b986-1cea83120c5a","isBot":false},{"t":64,"x":-222.26,"z":-321.59,"type":"Loot","user":"a58b4a5f-0add-43fe-b986-1cea83120c5a","isBot":false},{"t":79,"x":-185.39,"z":-306.68,"type":"BotKill","user":"a58b4a5f-0add-43fe-b986-1cea83120c5a","isBot":false},{"t":81,"x":-180.96,"z":-304.61,"type":"Loot","user":"a58b4a5f-0add-43fe-b986-1cea83120c5a","isBot":false},{"t":81,"x":-180.96,"z":-304.61,"type":"Loot","user":"a58b4a5f-0add-43fe-b986-1cea83120c5a","isBot":false},{"t":105,"x":-105.73,"z":-275.03,"type":"Loot","user":"a58b4a5f-0add-43fe-b986-1cea83120c5a","isBot":false},{"t":130,"x":-18.36,"z":-296.44,"type":"Loot","user":"a58b4a5f-0add-43fe-b986-1cea83120c5a","isBot":false},{"t":140,"x":-0.48,"z":-276.7,"type":"Loot","user":"a58b4a5f-0add-43fe-b986-1cea83120c5a","isBot":false},{"t":140,"x":-0.62,"z":-277.09,"type":"Loot","user":"a58b4a5f-0add-43fe-b986-1cea83120c5a","isBot":false},{"t":167,"x":-17.39,"z":-281.1,"type":"Loot","user":"a58b4a5f-0add-43fe-b986-1cea83120c5a","isBot":false},{"t":171,"x":-14.43,"z":-278.0,"type":"Loot","user":"a58b4a5f-0add-43fe-b986-1cea83120c5a","isBot":false},{"t":175,"x":-12.86,"z":-281.38,"type":"Loot","user":"a58b4a5f-0add-43fe-b986-1cea83120c5a","isBot":false},{"t":236,"x":-7.41,"z":-289.96,"type":"BotKill","user":"a58b4a5f-0add-43fe-b986-1cea83120c5a","isBot":false},{"t":240,"x":-8.19,"z":-300.1,"type":"Loot","user":"a58b4a5f-0add-43fe-b986-1cea83120c5a","isBot":false},{"t":242,"x":-7.86,"z":-300.07,"type":"Loot","user":"a58b4a5f-0add-43fe-b986-1cea83120c5a","isBot":false},{"t":263,"x":53.19,"z":-295.72,"type":"BotKill","user":"a58b4a5f-0add-43fe-b986-1cea83120c5a","isBot":false}]}