{"matchId":"825fe194-29df-48f7-bfec-f3d86e79c785.nakama-0","mapId":"AmbroseValley","date":"2026-02-12","startTs":1770897837,"durationSec":74,"humanCount":1,"botCount":0,"eventCounts":{"Position":11,"Loot":1,"BotKill":1,"BotKilled":1},"users":[{"id":"060a5173-6ed0-49ab-96d9-5b1b1406a72c","isBot":false,"path":[[0,-143.0,-193.04],[15,-143.57,-189.51],[20,-144.62,-180.88],[25,-133.81,-155.22],[30,-126.31,-127.03],[35,-128.58,-108.34],[40,-129.13,-103.6],[45,-131.97,-101.7],[55,-114.95,-89.96],[60,-91.98,-95.4],[65,-68.09,-92.08]]}],"events":[{"t":18,"x":-146.13,"z":-181.95,"type":"Loot","user":"060a5173-6ed0-49ab-96d9-5b1b1406a72c","isBot":false},{"t":69,"x":-67.77,"z":-91.8,"type":"BotKill","user":"060a5173-6ed0-49ab-96d9-5b1b1406a72c","isBot":false},{"t":74,"x":-69.44,"z":-90.86,"type":"BotKilled","user":"060a5173-6ed0-49ab-96d9-5b1b1406a72c","isBot":false}]}